kosh/__init__.py
kosh/core_sina.py
kosh/current_version.py
kosh/dataset.py
kosh/ensemble.py
kosh/kosh_command.py
kosh/lock_strategies.py
kosh/schema.py
kosh/store.py
kosh/threadsafe.py
kosh/threadsafe_decorators.py
kosh/utils.py
kosh/wrapper.py
kosh/exec_graphs/__init__.py
kosh/exec_graphs/core.py
kosh/loaders/UltraLoader.py
kosh/loaders/__init__.py
kosh/loaders/core.py
kosh/loaders/hdf5.py
kosh/loaders/jsons.py
kosh/loaders/npy.py
kosh/loaders/pandas_loader.py
kosh/loaders/pgm.py
kosh/loaders/pil.py
kosh/loaders/sidre.py
kosh/operators/__init__.py
kosh/operators/core.py
kosh/operators/koshClustering.py
kosh/operators/koshMaths.py
kosh/sampling_methods/__init__.py
kosh/sampling_methods/cluster_sampling/Clustering.py
kosh/sampling_methods/cluster_sampling/__init__.py
kosh/transformers/__init__.py
kosh/transformers/core.py
kosh/transformers/npy.py
kosh/transformers/sidre.py
kosh/transformers/skl.py
kosh/transformers/utils.py
kosh-3.3.0.data/scripts/kosh
kosh-3.3.0.data/scripts/kosh_command.py
kosh-3.3.0.data/scripts/sbang
kosh-3.3.0.dist-info/licenses/LICENSE
kosh-3.3.0.dist-info/licenses/NOTICE
kosh-3.3.0.dist-info/METADATA
kosh-3.3.0.dist-info/WHEEL
kosh-3.3.0.dist-info/top_level.txt
kosh-3.3.0.dist-info/RECORD
