Metadata-Version: 2.4
Name: kosh
Version: 3.3.0
Summary: Manages Data Store with External Bulk Data
Home-page: https://github.com/LLNL/Kosh
Author: Charles Doutriaux, Renee Olson
Author-email: doutriaux1@llnl.gov
License: MIT
Classifier: Programming Language :: Python
Classifier: License :: OSI Approved :: MIT License
Classifier: Operating System :: OS Independent
License-File: LICENSE
License-File: NOTICE
Requires-Dist: llnl-sina>=1.15.1
Requires-Dist: networkx>=2.6
Requires-Dist: numpy>=1.20
Requires-Dist: scipy
Requires-Dist: h5py>=3
Requires-Dist: scikit-learn>=1.0.2
Requires-Dist: pandas
Requires-Dist: hdbscan
Requires-Dist: matplotlib
Requires-Dist: tqdm
Requires-Dist: filelock
Dynamic: author
Dynamic: author-email
Dynamic: classifier
Dynamic: description
Dynamic: description-content-type
Dynamic: home-page
Dynamic: license
Dynamic: license-file
Dynamic: requires-dist
Dynamic: summary
